lz_validation/__init__.py
lz_validation/clang_tidy.py
lz_validation/cli.py
lz_validation/lz_validation.py
lz_validation/commands/__init__.py
lz_validation/commands/add_file_metrics.py
lz_validation/commands/compare_root_files.py
lz_validation/commands/execute_with_metrics.py
lz_validation/commands/get_target_branch.py
lz_validation/commands/inspect_branch_sizes.py
lz_validation/commands/merge_json.py
lz_validation/commands/print_root_content.py
lz_validation/io/__init__.py
lz_validation-0.0.4.dist-info/DESCRIPTION.rst
lz_validation-0.0.4.dist-info/METADATA
lz_validation-0.0.4.dist-info/RECORD
lz_validation-0.0.4.dist-info/WHEEL
lz_validation-0.0.4.dist-info/entry_points.txt
lz_validation-0.0.4.dist-info/metadata.json
lz_validation-0.0.4.dist-info/top_level.txt
