Metadata-Version: 2.0
Name: lz-validation
Version: 0.0.4
Summary: LZ physics validation package
Home-page: https://github.com/kreczko/lz_validation
Author: Luke Kreczko
Author-email: kreczko@cern.ch
License: Apache Software License 2.0
Keywords: lz_validation
Platform: UNKNOWN
Classifier: Development Status :: 2 - Pre-Alpha
Classifier: Intended Audience :: Developers
Classifier: License :: OSI Approved :: Apache Software License
Classifier: Natural Language :: English
Classifier: Programming Language :: Python :: 2
Classifier: Programming Language :: Python :: 2.7
Classifier: Programming Language :: Python :: 3
Classifier: Programming Language :: Python :: 3.4
Classifier: Programming Language :: Python :: 3.5
Classifier: Programming Language :: Python :: 3.6
Requires-Dist: Click (>=6.0)
Requires-Dist: matplotlib
Requires-Dist: python-gitlab
Requires-Dist: pandas
Requires-Dist: uproot
